PIOntologyExtractor/__init__.py
PIOntologyExtractor/DBManager.py
PIOntologyExtractor/Extractor/__init__.py
PIOntologyExtractor/Extractor/Extractor.py
PIOntologyExtractor/Visualizer.py
piontologyextractor-0.1.1.dist-info/WHEEL
piontologyextractor-0.1.1.dist-info/METADATA
piontologyextractor-0.1.1.dist-info/RECORD
