Metadata-Version: 2.1
Name: piontologyextractor
Version: 0.1.1
Summary: A package that can deal with extracting useful info from our Graph Ontology.
License: Pandora Intelligence
Author: David Berenstien
Author-email: david.berenstein@pandoraintelligence.com
Requires-Python: >=3.8,<4.0
Classifier: License :: Other/Proprietary License
Classifier: Programming Language :: Python :: 3
Classifier: Programming Language :: Python :: 3.8
Classifier: Programming Language :: Python :: 3.9
Requires-Dist: jaal (>=0.0.9,<0.0.10)
Requires-Dist: openpyxl (>=3.0.7,<4.0.0)
Requires-Dist: pandas (>=1.3.2,<2.0.0)
Requires-Dist: piauthorizer (>=0.9.5,<0.10.0)
